schulze_condorcet/__init__.py
schulze_condorcet/py.typed
schulze_condorcet/schulze_condorcet.py
schulze_condorcet/strength.py
schulze_condorcet/types.py
schulze_condorcet/util.py
schulze_condorcet-2.0.1.dist-info/LICENSE
schulze_condorcet-2.0.1.dist-info/METADATA
schulze_condorcet-2.0.1.dist-info/WHEEL
schulze_condorcet-2.0.1.dist-info/top_level.txt
schulze_condorcet-2.0.1.dist-info/RECORD
